PyQtThemeSettings/__init__.py
PyQtThemeSettings/settings.py
PyQtThemeSettings/ui/settingswindowUI.py
PyQtThemeSettings-1.0.2.post1.dist-info/LICENSE
PyQtThemeSettings-1.0.2.post1.dist-info/METADATA
PyQtThemeSettings-1.0.2.post1.dist-info/WHEEL
PyQtThemeSettings-1.0.2.post1.dist-info/top_level.txt
PyQtThemeSettings-1.0.2.post1.dist-info/RECORD
