Metadata-Version: 2.1
Name: PyQtThemeSettings
Version: 1.0.2.post1
Summary: A package for adding a theme management window to any PySide6 applications using PyQtDarkTheme
Author: MrSuspicious0
Project-URL: Homepage, https://github.com/MrSuspicious0/PyQtThemeSettings
Project-URL: Bug Tracker, https://github.com/MrSuspicious0/PyQtThemeSettings/issues
Keywords: pyqt,pyside,theme
Classifier: Programming Language :: Python :: 3.11
Classifier: Operating System :: OS Independent
Classifier: License :: OSI Approved :: MIT License
Classifier: Natural Language :: English
Requires-Python: >=3.11
License-File: LICENSE
Requires-Dist: pyqtdarktheme
Requires-Dist: pyside6
